waver/__init__.py
waver/_dock_widget.py
waver/_reader.py
waver/_version.py
waver/datasets/__init__.py
waver/datasets/_generator.py
waver/datasets/_loader.py
waver/datasets/_visualize.py
waver/simulation/__init__.py
waver/simulation/_convenience.py
waver/simulation/_detector.py
waver/simulation/_grid.py
waver/simulation/_source.py
waver/simulation/_time.py
waver/simulation/_utils.py
waver/simulation/_wave.py
waver/simulation/simulation.py
waver-0.0.4.dist-info/LICENSE
waver-0.0.4.dist-info/METADATA
waver-0.0.4.dist-info/WHEEL
waver-0.0.4.dist-info/entry_points.txt
waver-0.0.4.dist-info/top_level.txt
waver-0.0.4.dist-info/RECORD
