Metadata-Version: 2.1
Name: waver
Version: 0.0.4
Summary: Wave simulations
Home-page: https://github.com/sofroniewn/waver
Author: Nicholas Sofroniew
Author-email: sofroniewn@gmail.com
License: BSD-3
Platform: UNKNOWN
Classifier: Development Status :: 2 - Pre-Alpha
Classifier: Intended Audience :: Developers
Classifier: Framework :: napari
Classifier: Topic :: Software Development :: Testing
Classifier: Programming Language :: Python
Classifier: Programming Language :: Python :: 3
Classifier: Programming Language :: Python :: 3.7
Classifier: Programming Language :: Python :: 3.8
Classifier: Programming Language :: Python :: 3.9
Classifier: Operating System :: OS Independent
Classifier: License :: OSI Approved :: BSD License
Requires-Python: >=3.7
License-File: LICENSE
Requires-Dist: magicgui (>=0.2.10)
Requires-Dist: napari (>=0.4.10)
Requires-Dist: napari-plugin-engine (>=0.1.4)
Requires-Dist: numpy
Requires-Dist: zarr
